setup.cfg
setup.py
graphmap/__init__.py
graphmap/alpha_conversion.py
graphmap/amazon_s3.py
graphmap/azure_image_tree.py
graphmap/commander.py
graphmap/constants.py
graphmap/custom_errors.py
graphmap/decorators_library.py
graphmap/graph_helpers.py
graphmap/graphmap_main.py
graphmap/imagetree.py
graphmap/imagevalue.py
graphmap/interesting_sample_trees.py
graphmap/memory_persistence.py
graphmap/perf_tester.py
graphmap/persistence_interface.py
graphmap/pixel_approximator.py
graphmap/result.py
graphmap/samples.py
graphmap/serializer.py
graphmap/standard_nodes.py
graphmap/standard_pixel.py
graphmap/tile_disk_cache.py
graphmap/transforms.py
graphmap/tree_creator.py
graphmap/tree_operator.py
graphmap/tree_viewer.py
graphmap/treegenerator.py
graphmap/treemap.py
graphmap/utilities.py
graphmap.egg-info/PKG-INFO
graphmap.egg-info/SOURCES.txt
graphmap.egg-info/dependency_links.txt
graphmap.egg-info/top_level.txt
graphmap/serialization/__init__.py
graphmap/serialization/imagetree_pb2.py
graphmap/serialization/protbuf_serializer.py
graphmap/serialization/tsv_serializer.py