Metadata-Version: 1.1
Name: graphmap
Version: 0.0.6
Summary: Images on a quad graph. Create an infinite canvas
Home-page: https://github.com/abhishekraok/GraphMap
Author: Abhishek Rao
Author-email: abhishek.rao.comm@gmail.com
License: UNKNOWN
Download-URL: https://github.com/abhishekraok/GraphMap/archive/v0.0.4.tar.gz
Platform: UNKNOWN
